hcsim/__init__.py
hcsim/chisel_utils.py
hcsim/generate_barcode_bam.py
hcsim/main.py
hcsim/random_tree.py
hcsim/utils.py
hcsim/version.py
hcsim/bench/__init__.py
hcsim/bench/cnaccuracy.py
hcsim/bench/cnretain.py
hcsim/bench/cnstates.py
hcsim/bench/hcCNchange.py
hcsim/bench/hcidentify.py
hcsim/bench/hcparent.py
hcsim/bench/mirrorsubclone.py
hcsim/bench/subdetect.py
hcsim/bin/__init__.py
hcsim/bin/hcbench_main.py
hcsim/bin/hcsim_main.py
hcsim-1.3.0.dist-info/LICENSE
hcsim-1.3.0.dist-info/METADATA
hcsim-1.3.0.dist-info/WHEEL
hcsim-1.3.0.dist-info/entry_points.txt
hcsim-1.3.0.dist-info/top_level.txt
hcsim-1.3.0.dist-info/RECORD
