Metadata-Version: 2.2
Name: HCSIM
Version: 1.3.0
Summary: HCSIM: A Single-Cell Genomics Simulator with Haplotype-Specific Copy Number Annotation.
Home-page: https://github.com/xikanfeng2/HCSIM
Author: Xikang Feng
Author-email: Xikang Feng <fxk@nwpu.edu.cn>, Sisi Peng <sisipeng@mail.nwpu.edu.cn>
Maintainer: Sisi Peng
Maintainer-email: Xikang Feng <fxk@nwpu.edu.cn>
License: Copyright (c) 2024 The Python Packaging Authority
Project-URL: Homepage, https://github.com/xikanfeng2/HCSIM
Project-URL: Documentation, https://hcsim.readthedocs.org
Project-URL: Repository, https://github.com/xikanfeng2/HCSIM
Project-URL: Bug Tracker, https://github.com/me/spam/issues
Keywords: cancer,single-cell,DNA,copy-number,haplotype-specific,simulator
Classifier: Programming Language :: Python :: 3
Classifier: License :: OSI Approved :: MIT License
Classifier: Operating System :: OS Independent
Classifier: Topic :: Scientific/Engineering :: Bio-Informatics
Requires-Python: >=3.6
License-File: LICENSE
Requires-Dist: pandas
Requires-Dist: numpy<1.25,>=1.16.1
Requires-Dist: matplotlib>=3.0.2
Requires-Dist: networkx>=3.2.1
Requires-Dist: scikit-learn
Requires-Dist: biopython
Dynamic: author
Dynamic: home-page
Dynamic: maintainer
Dynamic: requires-python
